envencrypt/__init__.py
envencrypt/main.py
envencrypt/worker.py
envencrypt-0.3.0.dist-info/licenses/LICENSE
envencrypt-0.3.0.dist-info/WHEEL
envencrypt-0.3.0.dist-info/METADATA
envencrypt-0.3.0.dist-info/RECORD
