Metadata-Version: 2.4
Name: envencrypt
Version: 0.3.0
Summary: Windows DPAPI-based encryption/decryption library for .env files
Keywords: .env,encryption,decryption,dpapi
Author: Dyve ltd, Igor Petrovic
Author-email: Dyve ltd <dev@dyve.ch>, Igor Petrovic <758832+igorovic@users.noreply.github.com>
License-Expression: GPL-3.0-or-later
License-File: LICENSE
Classifier: Intended Audience :: Developers
Classifier: Operating System :: Microsoft :: Windows :: Windows 10
Classifier: Operating System :: Microsoft :: Windows :: Windows 11
Classifier: Programming Language :: Python :: 3
Classifier: Topic :: Software Development :: Quality Assurance
Classifier: Topic :: Software Development :: Libraries
Requires-Dist: dotenv>=0.9.9
Requires-Dist: pywin32>=311
Requires-Python: >=3.11
Project-URL: Homepage, https://github.com/Dyve-dev/py-envencrypt
Project-URL: Repository, https://github.com/Dyve-dev/py-envencrypt
